pypnpobjects/__init__.py
pypnpobjects/main.py
pypnpobjects/metadata.py
pypnpobjects/pypnpobjects.py
PyPnPObjects-0.1.9.dist-info/LICENSE
PyPnPObjects-0.1.9.dist-info/METADATA
PyPnPObjects-0.1.9.dist-info/WHEEL
PyPnPObjects-0.1.9.dist-info/entry_points.txt
PyPnPObjects-0.1.9.dist-info/top_level.txt
PyPnPObjects-0.1.9.dist-info/RECORD
