Metadata-Version: 2.1
Name: PyPnPObjects
Version: 0.1.9
Summary: 
Home-page: https://github.com/antaripchatterjee/PyPnPObjects
Author: Antarip Chatterjee
Author-email: antarip.chatterjee22@gmail.com
License: MIT
Platform: UNKNOWN
Classifier: License :: OSI Approved :: MIT License
Classifier: Operating System :: Microsoft :: Windows
Classifier: Programming Language :: Python :: 2.7
Classifier: Programming Language :: Python :: 3.5
Classifier: Programming Language :: Python :: 3.6
Classifier: Programming Language :: Python :: 3.7
Classifier: Programming Language :: Python :: 3.8
Classifier: Environment :: Console
Classifier: Development Status :: 4 - Beta
Classifier: Intended Audience :: End Users/Desktop
Classifier: Intended Audience :: Developers
Classifier: Intended Audience :: Education
Classifier: Topic :: System :: Hardware :: Hardware Drivers
